ioproc/__init__.py
ioproc/__main__.py
ioproc/actionmanager.py
ioproc/appconfig.py
ioproc/config.py
ioproc/datamanager.py
ioproc/defaults.py
ioproc/driver.py
ioproc/exceptions.py
ioproc/logger.py
ioproc/meta.py
ioproc/qualitychecks.py
ioproc/runners.py
ioproc/schemas.py
ioproc/texts.py
ioproc/tools.py
ioproc/templatefiles/create_folder_structure.py
ioproc/templatefiles/general.py
ioproc/templatefiles/noioproc.py
ioproc/templatefiles/run.py
ioproc/templatefiles/workflow.yaml
ioproc-2.3.0.dist-info/METADATA
ioproc-2.3.0.dist-info/WHEEL
ioproc-2.3.0.dist-info/entry_points.txt
ioproc-2.3.0.dist-info/licenses/LICENSE
ioproc-2.3.0.dist-info/RECORD
