Metadata-Version: 2.3
Name: ioproc
Version: 2.3.0
Summary: Workflow framework for data pre- and postprocessing.
Project-URL: homepage, https://gitlab.com/dlr-ve/ioproc
Author-email: Benjamin Fuchs <Benjamin.Fuchs@dlr.de>, Felix Nitsch <Felix.Nitsch@dlr.de>, Jan Buschmann <Jan.Buschmann@dlr.de>, Judith Riehm <Judith.Riehm@dlr.de>
Maintainer-email: Benjamin Fuchs <Benjamin.Fuchs@dlr.de>, Felix Nitsch <Felix.Nitsch@dlr.de>, Jan Buschmann <Jan.Buschmann@dlr.de>
License: Copyright 2020 Deutsches Zentrum für Luft- und Raumfahrt (DLR)
Keywords: data pipeline,data science,workflow management
Requires-Python: >=3.11
